[
  {
    "name": {
      "first": "Merle",
      "last": "Bryant"
    },
    "company": "ENOMEN"
  },
  {
    "name": {
      "first": "Mack",
      "last": "Owen"
    },
    "company": "MOTOVATE"
  },
  {
    "name": {
      "first": "Mcintosh",
      "last": "Mcdowell"
    },
    "company": "GORGANIC"
  },
  {
    "name": {
      "first": "Nielsen",
      "last": "Donovan"
    },
    "company": "ORBAXTER"
  },
  {
    "name": {
      "first": "Luz",
      "last": "Butler"
    },
    "company": "QOT"
  },
  {
    "name": {
      "first": "Stephenson",
      "last": "Marshall"
    },
    "company": "COMVEYER"
  },
  {
    "name": {
      "first": "Wanda",
      "last": "Mccall"
    },
    "company": "NETPLODE"
  },
  {
    "name": {
      "first": "Peters",
      "last": "Sanchez"
    },
    "company": "PRINTSPAN"
  }
]